LICENCE
MANIFEST.in
README.md
setup.py
allianceauth_corptools_indydash.egg-info/PKG-INFO
allianceauth_corptools_indydash.egg-info/SOURCES.txt
allianceauth_corptools_indydash.egg-info/dependency_links.txt
allianceauth_corptools_indydash.egg-info/requires.txt
allianceauth_corptools_indydash.egg-info/top_level.txt
indydash/__init__.py
indydash/admin.py
indydash/api.py
indydash/apps.py
indydash/auth_hooks.py
indydash/models.py
indydash/urls.py
indydash/views.py
indydash/migrations/0001_initial.py
indydash/migrations/0002_make_settings.py
indydash/migrations/__init__.py
indydash/static/indydash/asset-manifest.json
indydash/static/indydash/static/css/main.36543647.chunk.css
indydash/static/indydash/static/css/main.36543647.chunk.css.map
indydash/static/indydash/static/js/2.f48c1abc.chunk.js
indydash/static/indydash/static/js/2.f48c1abc.chunk.js.LICENSE.txt
indydash/static/indydash/static/js/2.f48c1abc.chunk.js.map
indydash/static/indydash/static/js/main.fd3c2074.chunk.js
indydash/static/indydash/static/js/main.fd3c2074.chunk.js.map
indydash/static/indydash/static/js/runtime-main.ff5b8ea4.js
indydash/static/indydash/static/js/runtime-main.ff5b8ea4.js.map
indydash/templates/indydash/react_base.html